libname/TOPSIS.py
libname/__init__.py
Topsis_Kishan_Pandey_102016114-0.0.13.dist-info/METADATA
Topsis_Kishan_Pandey_102016114-0.0.13.dist-info/WHEEL
Topsis_Kishan_Pandey_102016114-0.0.13.dist-info/top_level.txt
Topsis_Kishan_Pandey_102016114-0.0.13.dist-info/RECORD
