Metadata-Version: 2.1
Name: Topsis-Kishan_Pandey-102016114
Version: 0.0.13
Summary: Topsis code for calculation 
Home-page: UNKNOWN
Author: Kishan Pandey
Author-email: <kishanpandey.rkt@gmail.com>
License: UNKNOWN
Platform: UNKNOWN
Classifier: Development Status :: 1 - Planning
Classifier: Intended Audience :: Developers
Classifier: Programming Language :: Python :: 3
Classifier: Operating System :: Unix
Classifier: Operating System :: MacOS :: MacOS X
Classifier: Operating System :: Microsoft :: Windows
